README.md
setup.py
DynaUI/__init__.py
DynaUI/abstract.py
DynaUI/core.py
DynaUI/dialog.py
DynaUI/images.py
DynaUI/pixelate.py
DynaUI/utility.py
DynaUI/variable.py
DynaUI.egg-info/PKG-INFO
DynaUI.egg-info/SOURCES.txt
DynaUI.egg-info/dependency_links.txt
DynaUI.egg-info/not-zip-safe
DynaUI.egg-info/requires.txt
DynaUI.egg-info/top_level.txt
DynaUI/controls/__init__.py
DynaUI/controls/button.py
DynaUI/controls/container.py
DynaUI/controls/miscellaneous.py
DynaUI/controls/scrolled.py
DynaUI/demo/demo.py
DynaUI/demo/image1.png
DynaUI/demo/image2.png
DynaUI/demo/image3.png
DynaUI/demo/image4.jpg