Metadata-Version: 1.1
Name: DynaUI
Version: 1.1.1
Summary: A framework to increase the scalability and flexibility of wxPython
Home-page: https://github.com/yadizhou/DynaUI
Author: Yadi Zhou
Author-email: yadizhou90@gmail.com
License: GPL-3.0
Keywords: GUI UI wxPython user-interface
Platform: UNKNOWN
Classifier: Development Status :: 3 - Alpha
Classifier: Environment :: Win32 (MS Windows)
Classifier: Environment :: X11 Applications :: GTK
Classifier: Environment :: MacOS X :: Cocoa
Classifier: Operating System :: Microsoft :: Windows :: Windows 10
Classifier: Operating System :: Microsoft :: Windows :: Windows 7
Classifier: Operating System :: POSIX :: Linux
Classifier: Operating System :: MacOS :: MacOS X
Classifier: Intended Audience :: Developers
Classifier: Topic :: Software Development :: User Interfaces
Classifier: Programming Language :: Python :: 3.5
Classifier: Programming Language :: Python :: 3.6
